setup.py
cistern/__init__.py
cistern/cistern.py
cistern/migrations.py
cistern.egg-info/PKG-INFO
cistern.egg-info/SOURCES.txt
cistern.egg-info/dependency_links.txt
cistern.egg-info/entry_points.txt
cistern.egg-info/requires.txt
cistern.egg-info/top_level.txt